{
    "card":[
        {
            "id":1,
            "title":"Máy xét nghiệm huyết học tự động Excbio EH 8300",
            "content":"Hãng sản xuất: EXCBIO – Trung Quốc",
            "image":"./images/news-1.jpg"
        },
        {
            "id":1,
            "title":"Máy đo chức năng hô hấp Monitor SMP 21/01 RD",
            "content":" Hãng sx: Monitor Xuất xứ: Nga",
            "image":"./images/news-2.jpg"
        },
        {
            "id":1,
            "title":"Máy Holter huyết áp Labtech EC-ABP",
            "content":"Hãng sx: Labtech Xuất xứ: Hungary Liên hệ mua hàng: 0966648119",
            "image":"./images/news-3.jpg"
        },
        {
            "id":1,
            "title":"Ống môi trường vận chuyển vi rút",
            "content":"Hãng sản xuất: EXCBIO – Trung Quốc",
            "image":"./images/news-4.jpg"
        },
        {
            "id":1,
            "title":"Máy nội soi cổ tử cung Lianchuang LC-9100C",
            "content":"Hãng sản xuất: EXCBIO – Trung Quốc",
            "image":"./images/news-1.jpg"
        },
        {
            "id":1,
            "title":"Máy xét nghiệm huyết học tự động Excbio EH 8300",
            "content":"Hãng sản xuất: EXCBIO – Trung Quốc",
            "image":"./images/news-1.jpg"
        },
        {
            "id":1,
            "title":"Máy xét nghiệm huyết học tự động Excbio EH 8300",
            "content":"Hãng sản xuất: EXCBIO – Trung Quốc",
            "image":"./images/news-1.jpg"
        },
        {
            "id":1,
            "title":"Máy xét nghiệm huyết học tự động Excbio EH 8300",
            "content":"Hãng sản xuất: EXCBIO – Trung Quốc",
            "image":"./images/news-1.jpg"
        },
        {
            "id":1,
            "title":"Máy xét nghiệm huyết học tự động Excbio EH 8300",
            "content":"Hãng sản xuất: EXCBIO – Trung Quốc",
            "image":"./images/news-1.jpg"
        },
        {
            "id":1,
            "title":"Máy xét nghiệm huyết học tự động Excbio EH 8300",
            "content":"Hãng sản xuất: EXCBIO – Trung Quốc",
            "image":"./images/news-1.jpg"
        }
    ]
}